arena_rank/__init__.py
arena_rank/assets/logo-dark.png
arena_rank/assets/logo.png
arena_rank/models/__init__.py
arena_rank/models/bradley_terry.py
arena_rank/models/contextual_bradley_terry.py
arena_rank/models/rating_system.py
arena_rank/utils/__init__.py
arena_rank/utils/data_utils.py
arena_rank/utils/math_utils.py
arena_rank-0.1.1.dist-info/METADATA
arena_rank-0.1.1.dist-info/WHEEL
arena_rank-0.1.1.dist-info/licenses/LICENSE
arena_rank-0.1.1.dist-info/RECORD
