Metadata-Version: 2.4
Name: arena-rank
Version: 0.1.1
Summary: Ranking methodology powering the LMArena leaderboard.
Project-URL: Homepage, https://lmarena.ai
Project-URL: Repository, https://github.com/lmarena/arena-rank
Project-URL: Issues, https://github.com/lmarena/arena-rank/issues
Author-email: Clayton Thorrez <clayton@lmarena.ai>
License: Apache 2.0
License-File: LICENSE
Classifier: License :: OSI Approved :: Apache Software License
Classifier: Programming Language :: Python :: 3
Classifier: Programming Language :: Python :: 3.11
Classifier: Programming Language :: Python :: 3.12
Requires-Python: >=3.11
Requires-Dist: datasets
Requires-Dist: jax==0.8.1
Requires-Dist: jaxtyping
Requires-Dist: numpy==2.3.3
Requires-Dist: optax
Requires-Dist: pandas
